level2_order_book/__init__.py
level2_order_book/order_book.py
level2_order_book-0.1.1.dist-info/licenses/LICENSE
level2_order_book-0.1.1.dist-info/METADATA
level2_order_book-0.1.1.dist-info/WHEEL
level2_order_book-0.1.1.dist-info/top_level.txt
level2_order_book-0.1.1.dist-info/RECORD
