Metadata-Version: 2.4
Name: level2-order-book
Version: 0.1.1
Summary: A package for making order book from level 2 market data
Author-email: JasonJiang0303 <chinese88+0303@2925.com>
License-Expression: MIT
Project-URL: Homepage, https://github.com/JasonJiang0303/level2-order-book
Project-URL: Bug Tracker, https://github.com/JasonJiang0303/level2-order-book/issues
Classifier: Programming Language :: Python :: 3
Classifier: Operating System :: OS Independent
Requires-Python: >=3.7
License-File: LICENSE
Requires-Dist: l2data-reader>=0.1.14
Dynamic: license-file
